hdiprep/__init__.py
hdiprep/command_hdi_prep.py
hdiprep/parse_input.py
hdiprep/yaml_hdi_prep.py
hdiprep/HDIprep/__init__.py
hdiprep/HDIprep/fuzzy_operations.py
hdiprep/HDIprep/hdi_prep.py
hdiprep/HDIprep/morphology.py
hdiprep/HDIprep/utils.py
hdireg/__init__.py
hdireg/command_elastix.py
hdireg/command_transformix.py
hdireg/parse_input.py
hdireg/yaml_elastix.py
hdireg/HDIreg/__init__.py
hdireg/HDIreg/elastix.py
hdireg/HDIreg/tmp_elastix_registration.py
hdireg/HDIreg/tmp_registration_metrics.py
hdireg/HDIreg/transformix.py
hdireg/HDIreg/utils.py
patchmap/__init__.py
patchmap/aligned_umap.py
patchmap/distances.py
patchmap/layouts.py
patchmap/parametric_umap.py
patchmap/patchmap_.py
patchmap/plot.py
patchmap/sparse.py
patchmap/spectral.py
patchmap/utils.py
patchmap/validation.py
miaaim_python-0.0.1.dist-info/LICENSE
miaaim_python-0.0.1.dist-info/METADATA
miaaim_python-0.0.1.dist-info/WHEEL
miaaim_python-0.0.1.dist-info/top_level.txt
miaaim_python-0.0.1.dist-info/RECORD
