Metadata-Version: 2.1
Name: miaaim-python
Version: 0.0.1
Summary: Multi-omics Image Alignment and Analysis by Information Manifolds
Home-page: https://github.com/JoshuaHess12/miaaim-python
Maintainer: Joshua Hess
Maintainer-email: joshmhess12@gmail.com
License: MIT
Keywords: high-dimensional image imaging mulitplex manifold-learning
Platform: UNKNOWN
Classifier: Intended Audience :: Science/Research
Classifier: Intended Audience :: Developers
Classifier: License :: OSI Approved
Classifier: Programming Language :: Python
Classifier: Topic :: Software Development
Classifier: Topic :: Scientific/Engineering
Classifier: Operating System :: Microsoft :: Windows
Classifier: Operating System :: POSIX
Classifier: Operating System :: Unix
Classifier: Operating System :: MacOS
Classifier: Programming Language :: Python :: 3.6
Classifier: Programming Language :: Python :: 3.7
Classifier: Programming Language :: Python :: 3.8
Classifier: Programming Language :: Python :: 3.9
Requires-Dist: scikit-image (>=0.17.2)
Requires-Dist: numpy (>=1.19.5)
Requires-Dist: pandas (>=1.1.5)
Requires-Dist: pyimzML (>=1.4.1)
Requires-Dist: nibabel (>=3.2.1)
Requires-Dist: scipy (>=1.5.4)
Requires-Dist: h5py (>=3.1.0)
Requires-Dist: pathlib
Requires-Dist: umap-learn (>=0.5.1)
Requires-Dist: uncertainties
Requires-Dist: seaborn
Requires-Dist: matplotlib
Requires-Dist: scikit-learn
Requires-Dist: PyYAML
Requires-Dist: hdi-utils (==0.0.3.1)
